clinamen2/__init__.py
clinamen2/test_functions.py
clinamen2/cmaes/__init__.py
clinamen2/cmaes/cmaes_criteria.py
clinamen2/cmaes/params_and_state.py
clinamen2/cmaes/termination_criterion.py
clinamen2/runner/__init__.py
clinamen2/runner/basic_runner.py
clinamen2/utils/__init__.py
clinamen2/utils/bipop_restart.py
clinamen2/utils/file_handling.py
clinamen2/utils/jax_data.py
clinamen2/utils/lennard_jones.py
clinamen2/utils/neuralil_evaluation.py
clinamen2/utils/plot_functions.py
clinamen2/utils/script_functions.py
clinamen2/utils/structure_setup.py
Clinamen2-2024.7.1.dist-info/AUTHORS
Clinamen2-2024.7.1.dist-info/LICENSE
Clinamen2-2024.7.1.dist-info/METADATA
Clinamen2-2024.7.1.dist-info/NOTICE
Clinamen2-2024.7.1.dist-info/WHEEL
Clinamen2-2024.7.1.dist-info/top_level.txt
Clinamen2-2024.7.1.dist-info/RECORD
