Metadata-Version: 2.1
Name: Clinamen2
Version: 2024.7.1
Summary: a versatile implementation of the Cholesky CMA-ES
Author-email: Ralf Wanzenböck <ralf.wanzenboeck@tuwien.ac.at>
License: Apache License 2.0
Classifier: Development Status :: 5 - Production/Stable
Classifier: Operating System :: OS Independent
Classifier: Intended Audience :: Science/Research
Classifier: License :: OSI Approved :: Apache Software License
Classifier: Topic :: Scientific/Engineering :: Chemistry
Classifier: Topic :: Scientific/Engineering :: Physics
Classifier: Programming Language :: Python :: 3
Requires-Python: >=3.8
License-File: LICENSE
License-File: NOTICE
License-File: AUTHORS
Requires-Dist: ase >=3.22
Requires-Dist: numpy >=1.20
Requires-Dist: scipy >=1.8
Requires-Dist: dask >=2022.9.0
Requires-Dist: distributed >=2022.9.0
Requires-Dist: jinja2 >=3.1.2
Requires-Dist: dill >=0.3.5.1
Requires-Dist: tqdm >=4.63.0
Requires-Dist: packaging >=23.1
Provides-Extra: doc
Requires-Dist: sphinx ; extra == 'doc'
Requires-Dist: sphinx-autodoc-typehints ; extra == 'doc'
Requires-Dist: sphinx-rtd-theme ; extra == 'doc'
Provides-Extra: test
Requires-Dist: pytest ; extra == 'test'
Requires-Dist: pytest-datadir ; extra == 'test'
